swiftai/__init__.py
swiftai/hello.py
swiftai-0.1.dist-info/METADATA
swiftai-0.1.dist-info/RECORD
swiftai-0.1.dist-info/WHEEL
swiftai-0.1.dist-info/top_level.txt
